thppred/model/rf_model.onnx
thppred/model/xgb_model.onnx
thppred/python_scripts/thppred.py
thppred-1.1.dist-info/LICENSE.txt
thppred-1.1.dist-info/METADATA
thppred-1.1.dist-info/WHEEL
thppred-1.1.dist-info/entry_points.txt
thppred-1.1.dist-info/top_level.txt
thppred-1.1.dist-info/RECORD
