Metadata-Version: 2.1
Name: thppred
Version: 1.1
Summary: A tool for prediction of therapeutic peptides
Home-page: https://github.com/raghavagps/thppred
Requires-Python: >=3.6
License-File: LICENSE.txt
Requires-Dist: numpy
Requires-Dist: pandas
Requires-Dist: argparse
Requires-Dist: onnxruntime
